<?xml version="1.0" encoding="utf-8"?>
<!DOCTYPE hibernate-mapping PUBLIC "-//Hibernate/Hibernate Mapping DTD 3.0//EN"
		"http://hibernate.sourceforge.net/hibernate-mapping-3.0.dtd">
<!-- 
    Mapping file autogenerated by MyEclipse Persistence Tools
-->

<hibernate-mapping>
    <class name="virnet.management.entity.Apponitment" table="appointment" catalog="virnet">
        <id name="appointmentTimeId" type="java.lang.Integer">
            <column name="APPOINTMENT_TIME_ID" />
            <generator class="identity" />
        </id>
        <property name="appointmentCabinetId" type="java.lang.Integer">
            <column name="APPOINTMENT_CABINET_ID" length="65535" />
        </property>
    </class>
</hibernate-mapping>
